autonumber/__init__.py
autonumber/autonumber.py
autonumber-1.0.0.dist-info/LICENSE
autonumber-1.0.0.dist-info/METADATA
autonumber-1.0.0.dist-info/WHEEL
autonumber-1.0.0.dist-info/top_level.txt
autonumber-1.0.0.dist-info/RECORD
