Metadata-Version: 2.1
Name: autonumber
Version: 1.0.0
Summary: Useful utility that allows you to generate cell phone numbers of all countries of the world
Home-page: UNKNOWN
Author: UNKNOWN
Author-email: UNKNOWN
License: UNKNOWN
Keywords: list,awesome,generator,phonenumber,autonumber
Platform: UNKNOWN
